scanpars/__init__.py
scanpars/const.py
scanpars/lexer/__init__.py
scanpars/lexer/lexer.py
scanpars/lexer/utils.py
scanpars/parser/__init__.py
scanpars/parser/parser.py
scanpars/parser/repr.py
scanpars/parser/rule.py
scanpars/parser/syn.py
scanpars/parser/token.py
scanpars/parser/writer.py
scanpars-0.0.0.dist-info/LICENSE.md
scanpars-0.0.0.dist-info/METADATA
scanpars-0.0.0.dist-info/WHEEL
scanpars-0.0.0.dist-info/top_level.txt
scanpars-0.0.0.dist-info/RECORD
